djangocms_pai_mdl/__init__.py
djangocms_pai_mdl/apps.py
djangocms_pai_mdl/templates/djangocms_pai_mdl/base.html
djangocms_pai_mdl/templates/djangocms_pai_mdl/indigo-pink.html
djangocms_pai_mdl-0.0.1.dist-info/AUTHORS.rst
djangocms_pai_mdl-0.0.1.dist-info/LICENSE.txt
djangocms_pai_mdl-0.0.1.dist-info/METADATA
djangocms_pai_mdl-0.0.1.dist-info/WHEEL
djangocms_pai_mdl-0.0.1.dist-info/top_level.txt
djangocms_pai_mdl-0.0.1.dist-info/RECORD
